py_GB_tracks/__init__.py
py_GB_tracks/meta.py
py_GB_tracks/track_hub/__init__.py
py_GB_tracks/track_hub/genome_file.py
py_GB_tracks/track_hub/hub_file.py
py_GB_tracks/track_hub/track_hub.py
py_GB_tracks/tracks/__init__.py
py_GB_tracks/tracks/bam_track.py
py_GB_tracks/tracks/base_track.py
py_GB_tracks/tracks/bigbarchart_track.py
py_GB_tracks/tracks/bigbed_track.py
py_GB_tracks/tracks/bigchain_track.py
py_GB_tracks/tracks/biggenepred_track.py
py_GB_tracks/tracks/biginteract_track.py
py_GB_tracks/tracks/bigmaf_track.py
py_GB_tracks/tracks/bignarrowpeak_track.py
py_GB_tracks/tracks/bigpsl_track.py
py_GB_tracks/tracks/bigwig_track.py
py_GB_tracks/utilities/__init__.py
py_GB_tracks/utilities/color_scale.py
py_GB_tracks/utilities/default_hub.py
py_GB_tracks/utilities/logging.py
py_GB_tracks/utilities/wig_to_bed.py
py_GB_tracks-0.1.0.dist-info/LICENSE
py_GB_tracks-0.1.0.dist-info/METADATA
py_GB_tracks-0.1.0.dist-info/WHEEL
py_GB_tracks-0.1.0.dist-info/top_level.txt
py_GB_tracks-0.1.0.dist-info/RECORD
