Metadata-Version: 2.1
Name: py-GB-tracks
Version: 0.1.0
Summary: This package implements functions to generate a GenomBrowser trackhub from WGA analyses data
Home-page: UNKNOWN
Author: Romain Feron
Author-email: romain.feron.91@gmail.com
License: GPLv3
Platform: UNKNOWN
Classifier: License :: OSI Approved :: GNU General Public License v3 or later (GPLv3+)
Classifier: Programming Language :: Python
Classifier: Programming Language :: Python :: 3.6
Requires-Python: >=3.6.0
